{
  "parent": "l2backpack:backpacks/bag",
  "criteria": {
    "0": {
      "conditions": {
        "type": "COLLECT",
        "ingredient": [
          {
            "item": "l2backpack:armor_bag"
          },
          {
            "item": "l2backpack:book_bag"
          }
        ]
      },
      "trigger": "l2backpack:bag_interact"
    }
  },
  "display": {
    "description": {
      "translate": "advancements.l2backpack.backpacks.bag_collect.description"
    },
    "icon": {
      "count": 1,
      "id": "l2backpack:armor_bag"
    },
    "title": {
      "translate": "advancements.l2backpack.backpacks.bag_collect.title"
    }
  },
  "requirements": [
    [
      "0"
    ]
  ],
  "sends_telemetry_event": true
}